basis/__init__.py
basis/compat.py
basis/managers.py
basis/models.py
basis/serializers.py
django_basis-0.4.0.dist-info/DESCRIPTION.rst
django_basis-0.4.0.dist-info/METADATA
django_basis-0.4.0.dist-info/metadata.json
django_basis-0.4.0.dist-info/RECORD
django_basis-0.4.0.dist-info/top_level.txt
django_basis-0.4.0.dist-info/WHEEL
tests/__init__.py
tests/models.py
tests/serializers.py
tests/settings.py
tests/tests.py
tests/urls.py
tests/views.py
