Metadata-Version: 2.0
Name: django-basis
Version: 0.4.0
Summary: Simple reusable django app for basic model functionality
Home-page: http://github.com/frecar/django-basis
Author: Fredrik Carlsen
Author-email: fredrik@carlsen.io
License: MIT
Platform: UNKNOWN
Classifier: Programming Language :: Python
Classifier: Programming Language :: Python :: 2.7
Classifier: Programming Language :: Python :: 3.3
Classifier: Programming Language :: Python :: 3.4
Classifier: Topic :: Software Development :: Libraries :: Python Modules
Classifier: Framework :: Django
Classifier: Environment :: Web Environment
Classifier: Operating System :: OS Independent
Classifier: Natural Language :: English
